{
  "metadata": {
    "version": "1.0.0",
    "generatedAt": "2026-05-06T02:23:21.067715157Z",
    "templateType": "full_banner_conveyer",
    "propertyId": "b627d93e-a0ae-480a-a724-89bb3910550e",
    "homepageId": "79771788-f731-465c-b45b-d85d51d936f8"
  },
  "property": {
    "id": "b627d93e-a0ae-480a-a724-89bb3910550e",
    "name": "거제 핑스 애견펜션",
    "nameEn": "Geoje Pings Pet-Friendly Pension",
    "description": "",
    "subtitle": "",
    "address": "경남 거제시 장목면 거제북로 2738-2",
    "latitude": 34.9973305853919,
    "longitude": 128.692942926386,
    "contactPhone": "010-7574-4990",
    "contactEmail": "",
    "checkin": "15:00",
    "checkout": "11:00",
    "checkInOutInfo": "[입/퇴실 안내]\n- 입실시각: 15시\n- 퇴실시각: 11시\n※ 22시 이후 입실 시 펜션에 사전 문의 부탁드립니다.",
    "usageGuide": "[펜션 이용 안내 사항]\n- 전 객실 절대 금연입니다.\n- 미성년자는 보호자 동반 없이 이용하실 수 없습니다.\n- 다른 이용객에게 피해를 줄 수 있는 무분별한 오락, 음주, 고성방가는 삼가주시기 바랍니다.\n- 객실 및 주변 시설 이용 시 시설물의 훼손, 분실에 대한 책임은 투숙객에게 있으며, 손해배상의 책임을 질 수 있습니다.\n- 음식물 및 기타 쓰레기는 꼭 분리수거해 주시기 바랍니다.\n- 실내에서 고기, 생선 등 냄새가 심한 음식은 조리를 금지합니다.\n- 애견 운동장에서 바비큐 시 불꽃놀이 불멍은 금지입니다.\n\n[인원추가비(1박기준/현장결제)]\n- 만 5세이상~성인 10,000원\n※ 아동유아 기준인원 포함 / 최대인원 초과 불가\n\n[전 객실 개별바베큐]\n- 이용금액 : 20,000원 (1박기준/현장결제)\n- 제공품목 : 숯+그릴+바베큐통+장갑+집게+가위\n- 준비시간 : 입실시 ~ 23시\n- 이용시간 : 입실시 ~ 23시\n※ 숯 , 그릴, 버너 개인지참 불가\n※ 시간 관계없이 직접 토치 사용하여 이용\n\n[야외 공용수영장]\n- 운영기간 : 추후안내예정\n- 이용시간 : 입실시 ~ 21시 (연박시에만 오전 10시부터 가능)\n- 이용복장 : 면티 착용 가능\n\n※ 수영장 이용수칙\n- 수영 전 준비운동을 충분히 하고 이용해 주시기 바랍니다.\n- 다이빙은 절대 금지합니다. (※이용객의 부주의로 인한 사고에 대해서는 책임지지 않습니다.)\n- 유아 및 어린이는 반드시 보호자 동행 요망(유아와 어린이는 구명조끼를 반드시 착용해 주세요.)\n- 주변 바닥이 미끄러울 수 있으니 주의가 필요하며 유아 및 어린이 단독 출입을 제한합니다.\n- 물놀이는 응급사고의 위험이 있으므로, 수영장은 혼자 이용할 수 없습니다.\n- 수영장 내 음식물 반입 및 음주, 담배를 절대 금합니다.\n\n[애견운동장]\n- 반려견이 자유롭게 뛰어놀 수 있는 인조잔디\n\n[족구장]\n- 족구장 보유\n\n[전 객실 애견동반가능]\n- 최대마리수 : 901,902,903 2마리 / 904,905,906 3마리\n- 최대 kg수 : ~15kg 미만\n- 요금 : 1마리당 20,000원(1박기준/현장결제)\n※ 최대마리수 초과시 사전문의필수\n\n[편의시설]\n- 전 객실 Wi-Fi 이용 가능\n- 펜션 내 주차공간\n\n[승용차 이용시]\n ※ 네비게이션에 주소 또는 숙소명을 검색해주세요\n- 도로명 주소 : 경남 거제시 장목면 거제북로 2738-2\n\n[주변관광지]\n- 매미성\n- 거제관광모노레일\n- 유호리전망대\n- 거제저도유람선\n- 몽돌해변",
    "reservationGuide": "미성년자는 보호자 없이 예약 및 입실 불가하며, 위반 시 환불 없이 퇴실됩니다.\n객실 요금은 기준 인원 기준이며, 초과 시 추가 요금이 발생합니다.\n최대 인원 초과 시 입실 불가하며, 이로 인한 환불은 불가입니다. (유아, 어린이 포함)\n현장 추가 요금은 숙소 측에 사전 확인 바랍니다.\n수영장 등 부대시설은 날씨나 상황에 따라 이용이 제한될 수 있으니 사전 확인 바랍니다.\n당일 예약 후 취소 시 환불 불가하며, 늦은 시간 당일 예약 후 즉시 방문 시 입실 불가할 수 있으니 숙소 확인 후 예약해 주세요.\n취소 수수료는 구매처마다 다를 수 있습니다.\n시스템 오류로 인해 정상가와 다른 금액으로 예약이 진행된 경우, 부득이하게 예약이 취소될 수 있습니다.\n전 객실 금연이며, 흡연은 지정된 장소에서만 가능합니다.",
    "province": "경상남도",
    "city": "거제시",
    "domain": "pings.kr",
    "realtimeBookingId": "https://www.bookingplay.co.kr/booking/1/12008",
    "ybsId": "",
    "amenities": [ ],
    "nearbyAttractions": [
      "해변",
      "맛집",
      "수상스포츠"
    ],
    "services": [ ],
    "propertyThemes": [
      "오션뷰",
      "반려동물동반"
    ],
    "propertyTypes": [
      "펜션"
    ],
    "businessInfo": {
      "businessName": "핑스애견펜션",
      "businessNumber": "106-21-55773",
      "representativeName": "엄기백",
      "businessAddress": "경상남도 거제시 장목면 거제북로 2738-2",
      "businessPhone": "010-7574-4990",
      "businessEmail": "0000@naver.com",
      "businessType": "individual",
      "businessCategory": "숙박",
      "eCommerceRegistrationNumber": "",
      "ecommerceRegistrationNumber": ""
    },
    "contractInfo": {
      "contractStartDate": "2025-09-10T00:00:00.000Z",
      "contractEndDate": "2025-09-12T00:00:00.000Z",
      "contractStatus": "active",
      "contactName": "담당자명",
      "contactEmail": "담당자 이메일",
      "contactPhone": "담당자 전화번호",
      "paymentTerms": null,
      "cancellationPolicy": null,
      "bankName": "은행명",
      "accountNumber": "계좌번호",
      "accountHolder": "예금주",
      "commissionRate": 0,
      "securityDeposit": 0
    },
    "facilities": [
      {
        "id": "6daf2aca-47cf-4d8e-b234-9cd170eab290",
        "name": "전 객실 개별바베큐",
        "description": " ",
        "usageGuide": "- 이용금액 : 20,000원 (1박기준/현장결제)\n- 제공품목 : 숯+그릴+바베큐통+장갑+집게+가위\n- 준비시간 : 입실시 ~ 23시\n- 이용시간 : 입실시 ~ 23시\n※ 숯 , 그릴, 버너 개인지참 불가\n※ 시간 관계없이 직접 토치 사용하여 이용",
        "displayOrder": 165,
        "images": [ ]
      },
      {
        "id": "3e9b1cb0-627d-4b5a-aebe-bad118aacac1",
        "name": "야외 공용수영장",
        "description": " ",
        "usageGuide": "- 운영기간 : 추후안내예정\n- 이용시간 : 입실시 ~ 21시 (연박시에만 오전 10시부터 가능)\n- 이용복장 : 면티 착용 가능\n\n※ 수영장 이용수칙\n- 수영 전 준비운동을 충분히 하고 이용해 주시기 바랍니다.\n- 다이빙은 절대 금지합니다. (※이용객의 부주의로 인한 사고에 대해서는 책임지지 않습니다.)\n- 유아 및 어린이는 반드시 보호자 동행 요망(유아와 어린이는 구명조끼를 반드시 착용해 주세요.)\n- 주변 바닥이 미끄러울 수 있으니 주의가 필요하며 유아 및 어린이 단독 출입을 제한합니다.\n- 물놀이는 응급사고의 위험이 있으므로, 수영장은 혼자 이용할 수 없습니다.\n- 수영장 내 음식물 반입 및 음주, 담배를 절대 금합니다.",
        "displayOrder": 166,
        "images": [ ]
      },
      {
        "id": "cfc875b2-b94b-4898-84d9-499da68ea6d3",
        "name": "애견운동장",
        "description": " ",
        "usageGuide": "- 반려견이 자유롭게 뛰어놀 수 있는 인조잔디\n",
        "displayOrder": 167,
        "images": [ ]
      },
      {
        "id": "bdf0b69c-2718-4230-bc67-1b2b95534a84",
        "name": "족구장",
        "description": " ",
        "usageGuide": "- 족구장 보유",
        "displayOrder": 168,
        "images": [ ]
      },
      {
        "id": "0235a765-f514-4814-9662-c5b367d7aa6b",
        "name": "전 객실 애견동반가능",
        "description": " ",
        "usageGuide": "- 최대마리수 : 901,902,903 2마리 / 904,905,906 3마리\n- 최대 kg수 : ~15kg 미만\n- 요금 : 1마리당 20,000원(1박기준/현장결제)\n※ 최대마리수 초과시 사전문의필수",
        "displayOrder": 169,
        "images": [ ]
      }
    ],
    "refundPolicies": [
      {
        "refundProcessingDays": 9,
        "refundRate": 90
      },
      {
        "refundProcessingDays": 8,
        "refundRate": 80
      },
      {
        "refundProcessingDays": 7,
        "refundRate": 70
      },
      {
        "refundProcessingDays": 6,
        "refundRate": 60
      },
      {
        "refundProcessingDays": 5,
        "refundRate": 50
      },
      {
        "refundProcessingDays": 4,
        "refundRate": 40
      },
      {
        "refundProcessingDays": 3,
        "refundRate": 30
      },
      {
        "refundProcessingDays": 2,
        "refundRate": 20
      },
      {
        "refundProcessingDays": 1,
        "refundRate": 10
      },
      {
        "refundProcessingDays": 0,
        "refundRate": 0
      }
    ],
    "refundSettings": {
      "customerRefundNotice": "",
      "immediateRefundEnabled": false,
      "immediateRefundTimeLimit": "60"
    },
    "images": [
      {
        "thumbnail": [ ],
        "exterior": [ ],
        "surrounding": [ ],
        "commonArea": [ ]
      }
    ]
  },
  "rooms": [
    {
      "id": "298f1b0c-cf66-420c-b465-554e11cbbfb6",
      "name": "901(오션뷰, 테라스)",
      "description": "",
      "roomInfo": "원룸형, 거실1+침대룸(퀸침대1)+주방1+화장실1\n",
      "usageGuide": "",
      "group": null,
      "size": 33.06,
      "baseOccupancy": 2,
      "maxOccupancy": 2,
      "totalRoomCount": {
        "bedroom": 1,
        "bathroom": 1,
        "livingRoom": 1,
        "ondol": 0,
        "kitchen": 1
      },
      "bedTypes": [
        "퀸 베드"
      ],
      "amenities": [
        "침대",
        "테라스",
        "무료 WiFi",
        "스마트 TV",
        "에어컨",
        "냉장고",
        "헤어드라이어",
        "인덕션",
        "조리도구",
        "식기류",
        "화장실",
        "수건",
        "샴푸",
        "린스",
        "바디워시",
        "애견식기",
        "애견배변판",
        "애견어메니티",
        "개별바비큐"
      ],
      "roomViews": [
        "오션뷰"
      ],
      "roomStructures": [
        "원룸형"
      ],
      "status": "active",
      "timeSettings": {
        "timeSettingType": "property",
        "checkin": "15:00",
        "checkout": "11:00",
        "checkinDeadline": "22:00"
      },
      "roomOptions": {
        "petState": "Y",
        "poolState": "N",
        "barbecueState": "Y"
      },
      "images": [
        {
          "thumbnail": [ ],
          "interior": [ ],
          "exterior": [ ]
        }
      ],
      "displayOrder": 1
    },
    {
      "id": "b94df7e3-f799-4277-9a04-1aeee3b77d22",
      "name": "902(오션뷰, 테라스)",
      "description": "",
      "roomInfo": "원룸형, 거실1+침대룸(퀸침대1)+주방1+화장실1\n",
      "usageGuide": "",
      "group": null,
      "size": 33.06,
      "baseOccupancy": 2,
      "maxOccupancy": 2,
      "totalRoomCount": {
        "bedroom": 1,
        "bathroom": 1,
        "livingRoom": 1,
        "ondol": 0,
        "kitchen": 1
      },
      "bedTypes": [
        "퀸 베드"
      ],
      "amenities": [
        "침대",
        "테라스",
        "무료 WiFi",
        "스마트 TV",
        "에어컨",
        "냉장고",
        "헤어드라이어",
        "인덕션",
        "조리도구",
        "식기류",
        "화장실",
        "수건",
        "샴푸",
        "린스",
        "바디워시",
        "애견식기",
        "애견배변판",
        "애견어메니티",
        "개별바비큐"
      ],
      "roomViews": [
        "오션뷰"
      ],
      "roomStructures": [
        "원룸형"
      ],
      "status": "active",
      "timeSettings": {
        "timeSettingType": "property",
        "checkin": "15:00",
        "checkout": "11:00",
        "checkinDeadline": "22:00"
      },
      "roomOptions": {
        "petState": "Y",
        "poolState": "N",
        "barbecueState": "Y"
      },
      "images": [
        {
          "thumbnail": [ ],
          "interior": [ ],
          "exterior": [ ]
        }
      ],
      "displayOrder": 2
    },
    {
      "id": "c1207a0e-fb6a-4164-be47-2bb56b97b668",
      "name": "903(오션뷰, 테라스)",
      "description": "",
      "roomInfo": "원룸형, 거실1+침대룸(퀸침대1)+주방1+화장실1\n",
      "usageGuide": "",
      "group": null,
      "size": 33.06,
      "baseOccupancy": 2,
      "maxOccupancy": 2,
      "totalRoomCount": {
        "bedroom": 1,
        "bathroom": 1,
        "livingRoom": 1,
        "ondol": 0,
        "kitchen": 1
      },
      "bedTypes": [
        "퀸 베드"
      ],
      "amenities": [
        "침대",
        "테라스",
        "무료 WiFi",
        "스마트 TV",
        "에어컨",
        "냉장고",
        "헤어드라이어",
        "인덕션",
        "조리도구",
        "식기류",
        "화장실",
        "수건",
        "샴푸",
        "린스",
        "바디워시",
        "애견식기",
        "애견배변판",
        "애견어메니티",
        "개별바비큐"
      ],
      "roomViews": [
        "오션뷰"
      ],
      "roomStructures": [
        "원룸형"
      ],
      "status": "active",
      "timeSettings": {
        "timeSettingType": "property",
        "checkin": "15:00",
        "checkout": "11:00",
        "checkinDeadline": "22:00"
      },
      "roomOptions": {
        "petState": "Y",
        "poolState": "N",
        "barbecueState": "Y"
      },
      "images": [
        {
          "thumbnail": [ ],
          "interior": [ ],
          "exterior": [ ]
        }
      ],
      "displayOrder": 3
    },
    {
      "id": "8094c6be-3741-4a69-be5d-b35f2f1622a9",
      "name": "904(오션뷰, 테라스)",
      "description": "",
      "roomInfo": "복층형, 거실1+침대룸(퀸침대1)+주방1+화장실1\n",
      "usageGuide": "",
      "group": null,
      "size": 49.59,
      "baseOccupancy": 4,
      "maxOccupancy": 6,
      "totalRoomCount": {
        "bedroom": 1,
        "bathroom": 1,
        "livingRoom": 1,
        "ondol": 0,
        "kitchen": 1
      },
      "bedTypes": [
        "퀸 베드"
      ],
      "amenities": [
        "침대",
        "테라스",
        "무료 WiFi",
        "스마트 TV",
        "에어컨",
        "냉장고",
        "헤어드라이어",
        "인덕션",
        "조리도구",
        "식기류",
        "화장실",
        "수건",
        "샴푸",
        "린스",
        "바디워시",
        "애견식기",
        "애견배변판",
        "애견어메니티",
        "개별바비큐"
      ],
      "roomViews": [
        "오션뷰"
      ],
      "roomStructures": [
        "복층"
      ],
      "status": "active",
      "timeSettings": {
        "timeSettingType": "property",
        "checkin": "15:00",
        "checkout": "11:00",
        "checkinDeadline": "22:00"
      },
      "roomOptions": {
        "petState": "Y",
        "poolState": "N",
        "barbecueState": "Y"
      },
      "images": [
        {
          "thumbnail": [ ],
          "interior": [ ],
          "exterior": [ ]
        }
      ],
      "displayOrder": 4
    },
    {
      "id": "9e50933d-e92c-40d1-b5a9-17df7ab199b1",
      "name": "905(오션뷰, 테라스)",
      "description": "",
      "roomInfo": "복층형, 거실1+침대룸(퀸침대1)+주방1+화장실1\n",
      "usageGuide": "",
      "group": null,
      "size": 49.59,
      "baseOccupancy": 4,
      "maxOccupancy": 6,
      "totalRoomCount": {
        "bedroom": 1,
        "bathroom": 1,
        "livingRoom": 1,
        "ondol": 0,
        "kitchen": 1
      },
      "bedTypes": [
        "퀸 베드"
      ],
      "amenities": [
        "침대",
        "테라스",
        "무료 WiFi",
        "스마트 TV",
        "에어컨",
        "냉장고",
        "헤어드라이어",
        "인덕션",
        "조리도구",
        "식기류",
        "화장실",
        "수건",
        "샴푸",
        "린스",
        "바디워시",
        "애견식기",
        "애견배변판",
        "애견어메니티",
        "개별바비큐"
      ],
      "roomViews": [
        "오션뷰"
      ],
      "roomStructures": [
        "복층"
      ],
      "status": "active",
      "timeSettings": {
        "timeSettingType": "property",
        "checkin": "15:00",
        "checkout": "11:00",
        "checkinDeadline": "22:00"
      },
      "roomOptions": {
        "petState": "Y",
        "poolState": "N",
        "barbecueState": "Y"
      },
      "images": [
        {
          "thumbnail": [ ],
          "interior": [ ],
          "exterior": [ ]
        }
      ],
      "displayOrder": 5
    },
    {
      "id": "48fea512-d747-4ff0-94ea-7d3d2b379f58",
      "name": "906(오션뷰, 테라스)",
      "description": "",
      "roomInfo": "복층형, 거실1+침대룸(퀸침대1)+주방1+화장실1\n",
      "usageGuide": "",
      "group": null,
      "size": 49.59,
      "baseOccupancy": 4,
      "maxOccupancy": 6,
      "totalRoomCount": {
        "bedroom": 1,
        "bathroom": 1,
        "livingRoom": 1,
        "ondol": 0,
        "kitchen": 1
      },
      "bedTypes": [
        "퀸 베드"
      ],
      "amenities": [
        "침대",
        "테라스",
        "무료 WiFi",
        "스마트 TV",
        "에어컨",
        "냉장고",
        "헤어드라이어",
        "인덕션",
        "조리도구",
        "식기류",
        "화장실",
        "수건",
        "샴푸",
        "린스",
        "바디워시",
        "애견식기",
        "애견배변판",
        "애견어메니티",
        "개별바비큐"
      ],
      "roomViews": [
        "오션뷰"
      ],
      "roomStructures": [
        "복층"
      ],
      "status": "active",
      "timeSettings": {
        "timeSettingType": "property",
        "checkin": "15:00",
        "checkout": "11:00",
        "checkinDeadline": "22:00"
      },
      "roomOptions": {
        "petState": "Y",
        "poolState": "N",
        "barbecueState": "Y"
      },
      "images": [
        {
          "thumbnail": [ ],
          "interior": [ ],
          "exterior": [ ]
        }
      ],
      "displayOrder": 6
    }
  ],
  "homepage": {
    "id": "79771788-f731-465c-b45b-d85d51d936f8",
    "domain": "pings.kr",
    "templateType": "full_banner_conveyer",
    "images": [
      {
        "logo": [ ]
      }
    ],
    "seo": {
      "title": "거제 핑스 애견펜션",
      "description": "거제 핑스 애견펜션, 반려견과 함께 즐기는 감성 오션뷰 숙소",
      "keywords": "거제펜션,거제숙소,거제애견,거제반려견,애견펜션,반려견동반"
    },
    "socialLinks": {
      "facebook": null,
      "instagram": null,
      "blog": null,
      "youtube": null
    },
    "customFields": {
      "pages": {
        "index": {
          "sections": [
            {
              "hero": {
                "title": "거제 핑스 애견펜션",
                "images": [
                  {
                    "id": "887a9984-b1f7-42bf-9f28-0eaf7866c690",
                    "url": "https://jlnjajtcnyqupfaqjerz.supabase.co/storage/v1/object/public/app-images/homepage/79771788-f731-465c-b45b-d85d51d936f8/index_hero/1778033801176-6zy62mmdoz.jpg",
                    "sortOrder": 0,
                    "description": "",
                    "isSelected": true,
                    "blockId": null
                  },
                  {
                    "id": "1db88529-db38-44dd-90ec-f7ac61179fc2",
                    "url": "https://jlnjajtcnyqupfaqjerz.supabase.co/storage/v1/object/public/app-images/homepage/79771788-f731-465c-b45b-d85d51d936f8/index_hero/1778033801203-lfnvkcewxy.jpg",
                    "sortOrder": 1,
                    "description": "",
                    "isSelected": true,
                    "blockId": null
                  },
                  {
                    "id": "ace9bbf7-8b54-4147-a2c2-a58d693b5c66",
                    "url": "https://jlnjajtcnyqupfaqjerz.supabase.co/storage/v1/object/public/app-images/homepage/79771788-f731-465c-b45b-d85d51d936f8/index_hero/1778033801201-8zl19enzef.jpg",
                    "sortOrder": 2,
                    "description": "",
                    "isSelected": true,
                    "blockId": null
                  },
                  {
                    "id": "51f98bc5-f307-4840-877c-24edefa6d90c",
                    "url": "https://jlnjajtcnyqupfaqjerz.supabase.co/storage/v1/object/public/app-images/homepage/79771788-f731-465c-b45b-d85d51d936f8/index_hero/1778033801327-0bxihxxovv.jpg",
                    "sortOrder": 3,
                    "description": "",
                    "isSelected": true,
                    "blockId": null
                  },
                  {
                    "id": "a8629b4b-2217-4e88-8eeb-92ccd29cbbff",
                    "url": "https://jlnjajtcnyqupfaqjerz.supabase.co/storage/v1/object/public/app-images/homepage/79771788-f731-465c-b45b-d85d51d936f8/index_hero/1778033801325-mo6we7fmjn.jpg",
                    "sortOrder": 4,
                    "description": "",
                    "isSelected": true,
                    "blockId": null
                  },
                  {
                    "id": "3edbd0cd-a055-4a68-9aed-ed43d74c76bb",
                    "url": "https://jlnjajtcnyqupfaqjerz.supabase.co/storage/v1/object/public/app-images/homepage/79771788-f731-465c-b45b-d85d51d936f8/index_hero/1778033801325-73tyj21tre.jpg",
                    "sortOrder": 5,
                    "description": "",
                    "isSelected": true,
                    "blockId": null
                  },
                  {
                    "id": "b39cc0ee-9f7e-4646-bc60-ccaa3bd5800d",
                    "url": "https://jlnjajtcnyqupfaqjerz.supabase.co/storage/v1/object/public/app-images/homepage/79771788-f731-465c-b45b-d85d51d936f8/index_hero/1778033801272-ik19fryaoc.jpg",
                    "sortOrder": 6,
                    "description": "",
                    "isSelected": true,
                    "blockId": null
                  },
                  {
                    "id": "70e0c060-7d6b-406c-8baa-0a4f59c2d160",
                    "url": "https://jlnjajtcnyqupfaqjerz.supabase.co/storage/v1/object/public/app-images/homepage/79771788-f731-465c-b45b-d85d51d936f8/index_hero/1778033801227-yhoik8af5o.jpg",
                    "sortOrder": 7,
                    "description": "",
                    "isSelected": true,
                    "blockId": null
                  },
                  {
                    "id": "46a5bc8b-5cfe-4b89-894f-fdf8c68bfc07",
                    "url": "https://jlnjajtcnyqupfaqjerz.supabase.co/storage/v1/object/public/app-images/homepage/79771788-f731-465c-b45b-d85d51d936f8/index_hero/1778033801369-47ccxifzsp.jpg",
                    "sortOrder": 8,
                    "description": "",
                    "isSelected": true,
                    "blockId": null
                  },
                  {
                    "id": "8430e35c-3115-46ba-9ba8-928d0ec94e60",
                    "url": "https://jlnjajtcnyqupfaqjerz.supabase.co/storage/v1/object/public/app-images/homepage/79771788-f731-465c-b45b-d85d51d936f8/index_hero/1778033801327-4itasvgd09.jpg",
                    "sortOrder": 9,
                    "description": "",
                    "isSelected": true,
                    "blockId": null
                  }
                ],
                "videos": [ ],
                "mediaType": "image",
                "description": " "
              },
              "closing": {
                "title": " ",
                "images": [
                  {
                    "id": "7d2be713-bcc5-4c11-8829-65de3c18d8b7",
                    "url": "https://jlnjajtcnyqupfaqjerz.supabase.co/storage/v1/object/public/app-images/homepage/79771788-f731-465c-b45b-d85d51d936f8/index_closing/1778034067482-wytyjq9ugu.jpg",
                    "sortOrder": 0,
                    "description": "",
                    "isSelected": true,
                    "blockId": null
                  }
                ],
                "videos": [ ],
                "mediaType": "image",
                "description": " "
              },
              "essence": {
                "title": "거제 핑스 애견펜션",
                "images": [
                  {
                    "id": "0c7bab53-00a0-4c1d-b49e-7973f509ed07",
                    "url": "https://jlnjajtcnyqupfaqjerz.supabase.co/storage/v1/object/public/app-images/homepage/79771788-f731-465c-b45b-d85d51d936f8/index_essence/1778034175012-f9dig02qr6.jpg",
                    "sortOrder": 0,
                    "description": "",
                    "isSelected": true,
                    "blockId": null
                  },
                  {
                    "id": "1473cb73-4917-4407-ad44-3256827f27e4",
                    "url": "https://jlnjajtcnyqupfaqjerz.supabase.co/storage/v1/object/public/app-images/homepage/79771788-f731-465c-b45b-d85d51d936f8/index_essence/1778034175046-esxw2qfl0n.jpg",
                    "sortOrder": 1,
                    "description": "",
                    "isSelected": true,
                    "blockId": null
                  },
                  {
                    "id": "71e20e10-c75f-4da5-8b38-f438a0a78122",
                    "url": "https://jlnjajtcnyqupfaqjerz.supabase.co/storage/v1/object/public/app-images/homepage/79771788-f731-465c-b45b-d85d51d936f8/index_essence/1778034175038-p9kqpo50g3.jpg",
                    "sortOrder": 2,
                    "description": "",
                    "isSelected": true,
                    "blockId": null
                  }
                ],
                "videos": [ ],
                "mediaType": "image",
                "description": "거제 바다를 담은 오션뷰 애견펜션.\n숙소 앞 해변에서 반려견과 산책과 힐링을 즐겨보세요.\n감성 가득한 공간에서 특별한 추억을 만들어드립니다.\n바다와 반려견, 휴식을 함께 누려보세요."
              },
              "gallery": {
                "title": "Preview",
                "images": [
                  {
                    "id": "095e4e23-2080-4639-bbe2-b2d0b13fe0fe",
                    "url": "https://jlnjajtcnyqupfaqjerz.supabase.co/storage/v1/object/public/app-images/homepage/79771788-f731-465c-b45b-d85d51d936f8/index_gallery/1778034067432-o268k30veh.jpg",
                    "sortOrder": 0,
                    "description": "",
                    "isSelected": true,
                    "blockId": null
                  },
                  {
                    "id": "4dd76000-fe2a-4e52-9033-e4bfb0863581",
                    "url": "https://jlnjajtcnyqupfaqjerz.supabase.co/storage/v1/object/public/app-images/homepage/79771788-f731-465c-b45b-d85d51d936f8/index_gallery/1778034067470-9lxdtyrlfd.jpg",
                    "sortOrder": 1,
                    "description": "",
                    "isSelected": true,
                    "blockId": null
                  },
                  {
                    "id": "50092db4-f484-420b-b97c-7e851b11c0dc",
                    "url": "https://jlnjajtcnyqupfaqjerz.supabase.co/storage/v1/object/public/app-images/homepage/79771788-f731-465c-b45b-d85d51d936f8/index_gallery/1778034067468-3k9ckxgpra.jpg",
                    "sortOrder": 2,
                    "description": "",
                    "isSelected": true,
                    "blockId": null
                  },
                  {
                    "id": "446c38ac-9fac-4509-9198-92455dd8df18",
                    "url": "https://jlnjajtcnyqupfaqjerz.supabase.co/storage/v1/object/public/app-images/homepage/79771788-f731-465c-b45b-d85d51d936f8/index_gallery/1778034067451-rec6l2xc96.jpg",
                    "sortOrder": 3,
                    "description": "",
                    "isSelected": true,
                    "blockId": null
                  },
                  {
                    "id": "ded83664-bb8e-4103-9ac0-85f0fac85f7f",
                    "url": "https://jlnjajtcnyqupfaqjerz.supabase.co/storage/v1/object/public/app-images/homepage/79771788-f731-465c-b45b-d85d51d936f8/index_gallery/1778034067466-ps5j0me0l3.jpg",
                    "sortOrder": 4,
                    "description": "",
                    "isSelected": true,
                    "blockId": null
                  },
                  {
                    "id": "3e0e3964-4281-409e-8fab-f7f2118b1a6c",
                    "url": "https://jlnjajtcnyqupfaqjerz.supabase.co/storage/v1/object/public/app-images/homepage/79771788-f731-465c-b45b-d85d51d936f8/index_gallery/1778034067473-tvnh70qkn8.jpg",
                    "sortOrder": 5,
                    "description": "",
                    "isSelected": true,
                    "blockId": null
                  },
                  {
                    "id": "ef92839d-de55-41a9-bfda-d40dc39910d4",
                    "url": "https://jlnjajtcnyqupfaqjerz.supabase.co/storage/v1/object/public/app-images/homepage/79771788-f731-465c-b45b-d85d51d936f8/index_gallery/1778034067487-2krx7wnqan.jpg",
                    "sortOrder": 6,
                    "description": "",
                    "isSelected": true,
                    "blockId": null
                  }
                ],
                "videos": [ ],
                "mediaType": "image",
                "description": " "
              },
              "signature": {
                "title": "",
                "images": [ ],
                "videos": [ ],
                "mediaType": "image"
              }
            }
          ]
        },
        "directions": {
          "sections": [
            {
              "hero": {
                "title": "",
                "images": [
                  {
                    "id": "68553efb-e169-4866-a799-e960f704eac3",
                    "url": "https://jlnjajtcnyqupfaqjerz.supabase.co/storage/v1/object/public/app-images/homepage/79771788-f731-465c-b45b-d85d51d936f8/directions_hero/1778033801368-u20puob9fn.jpg",
                    "sortOrder": 0,
                    "description": "",
                    "isSelected": true,
                    "blockId": null
                  }
                ]
              },
              "notice": {
                "title": "",
                "description": ""
              }
            }
          ]
        },
        "main": {
          "sections": [
            {
              "hero": {
                "title": "",
                "images": [
                  {
                    "id": "5f40b159-fa29-4aa9-b49a-05fcdb2a75f6",
                    "url": "https://jlnjajtcnyqupfaqjerz.supabase.co/storage/v1/object/public/app-images/homepage/79771788-f731-465c-b45b-d85d51d936f8/main_hero/1778033801329-h84vrctv4b.jpg",
                    "sortOrder": 0,
                    "description": "",
                    "isSelected": true,
                    "blockId": null
                  }
                ]
              },
              "about": [ ]
            }
          ]
        },
        "room": [ ],
        "facility": [ ],
        "reservation": {
          "sections": [
            {
              "hero": {
                "title": "",
                "images": [
                  {
                    "id": "7960d826-7676-487e-9982-4f93f4af4da7",
                    "url": "https://jlnjajtcnyqupfaqjerz.supabase.co/storage/v1/object/public/app-images/homepage/79771788-f731-465c-b45b-d85d51d936f8/reservation_hero/1778033801370-gvhmzhugnx.jpg",
                    "sortOrder": 0,
                    "description": "",
                    "isSelected": true,
                    "blockId": null
                  }
                ]
              },
              "about": {
                "title": "",
                "images": [ ],
                "description": ""
              }
            }
          ]
        }
      },
      "popup": {
        "popups": [ ]
      },
      "theme": {
        "font": {
          "koMain": {
            "cdn": null,
            "key": "imhyemin",
            "woff2": "https://cdn.jsdelivr.net/gh/projectnoonnu/noonfonts_2106@1.1/IM_Hyemin-Regular.woff2",
            "family": "ImHyeMin"
          },
          "koSub": {
            "cdn": "https://cdn.jsdelivr.net/gh/orioncactus/pretendard/dist/web/static/pretendard.min.css",
            "key": "pretendard",
            "woff2": null,
            "family": "Pretendard"
          },
          "enMain": {
            "cdn": "https://fonts.googleapis.com/css2?family=Cormorant:ital,wght@0,300..700;1,300..700&display=swap",
            "key": "cormorant",
            "woff2": null,
            "family": "Cormorant"
          }
        },
        "color": null
      },
      "property": {
        "name": "거제 핑스 애견펜션",
        "images": [ ],
        "nameEn": "Geoje Pings Pet-Friendly Pension"
      },
      "roomtypes": [
        {
          "id": "298f1b0c-cf66-420c-b465-554e11cbbfb6",
          "images": [
            {
              "id": "56d31e84-14b4-4db3-b0fe-0c062ef35f5f",
              "url": "https://jlnjajtcnyqupfaqjerz.supabase.co/storage/v1/object/public/app-images/homepage/79771788-f731-465c-b45b-d85d51d936f8/roomtype_thumbnail/1778033102376-61rl62lveq.jpg",
              "sortOrder": 0,
              "description": "",
              "isSelected": true,
              "blockId": "298f1b0c-cf66-420c-b465-554e11cbbfb6",
              "category": "roomtype_thumbnail"
            },
            {
              "id": "2e6ce538-3a7d-460c-820d-f9fa90231e78",
              "url": "https://jlnjajtcnyqupfaqjerz.supabase.co/storage/v1/object/public/app-images/homepage/79771788-f731-465c-b45b-d85d51d936f8/roomtype_interior/1778033102373-hxrnikw7o3.jpg",
              "sortOrder": 0,
              "description": "",
              "isSelected": true,
              "blockId": "298f1b0c-cf66-420c-b465-554e11cbbfb6",
              "category": "roomtype_interior"
            },
            {
              "id": "09965f60-23dd-4e22-8960-bd848f42bdb3",
              "url": "https://jlnjajtcnyqupfaqjerz.supabase.co/storage/v1/object/public/app-images/homepage/79771788-f731-465c-b45b-d85d51d936f8/roomtype_interior/1778033102377-uhpdhof9o0.jpg",
              "sortOrder": 1,
              "description": "",
              "isSelected": true,
              "blockId": "298f1b0c-cf66-420c-b465-554e11cbbfb6",
              "category": "roomtype_interior"
            },
            {
              "id": "bbbc15e4-2e59-43e6-af3e-5de0bfa6559e",
              "url": "https://jlnjajtcnyqupfaqjerz.supabase.co/storage/v1/object/public/app-images/homepage/79771788-f731-465c-b45b-d85d51d936f8/roomtype_interior/1778033102475-lqduvzwu3a.jpg",
              "sortOrder": 2,
              "description": "",
              "isSelected": true,
              "blockId": "298f1b0c-cf66-420c-b465-554e11cbbfb6",
              "category": "roomtype_interior"
            },
            {
              "id": "81faba60-c7c5-4518-942f-6dcddf2a7c89",
              "url": "https://jlnjajtcnyqupfaqjerz.supabase.co/storage/v1/object/public/app-images/homepage/79771788-f731-465c-b45b-d85d51d936f8/roomtype_interior/1778033102477-gzp620k94e.jpg",
              "sortOrder": 3,
              "description": "",
              "isSelected": true,
              "blockId": "298f1b0c-cf66-420c-b465-554e11cbbfb6",
              "category": "roomtype_interior"
            },
            {
              "id": "51701e91-f9fd-4f5a-83c1-8e27387550bc",
              "url": "https://jlnjajtcnyqupfaqjerz.supabase.co/storage/v1/object/public/app-images/homepage/79771788-f731-465c-b45b-d85d51d936f8/roomtype_interior/1778033102378-zy3tdbkvsz.jpg",
              "sortOrder": 4,
              "description": "",
              "isSelected": true,
              "blockId": "298f1b0c-cf66-420c-b465-554e11cbbfb6",
              "category": "roomtype_interior"
            },
            {
              "id": "76947fb8-d585-4b33-864e-f6ca4e79fa22",
              "url": "https://jlnjajtcnyqupfaqjerz.supabase.co/storage/v1/object/public/app-images/homepage/79771788-f731-465c-b45b-d85d51d936f8/roomtype_interior/1778033102472-ghwtjx6ta7.jpg",
              "sortOrder": 5,
              "description": "",
              "isSelected": true,
              "blockId": "298f1b0c-cf66-420c-b465-554e11cbbfb6",
              "category": "roomtype_interior"
            },
            {
              "id": "46cdab4e-1894-462b-9c41-40d83d65d21d",
              "url": "https://jlnjajtcnyqupfaqjerz.supabase.co/storage/v1/object/public/app-images/homepage/79771788-f731-465c-b45b-d85d51d936f8/roomtype_interior/1778033102473-59wypabtey.jpg",
              "sortOrder": 6,
              "description": "",
              "isSelected": true,
              "blockId": "298f1b0c-cf66-420c-b465-554e11cbbfb6",
              "category": "roomtype_interior"
            },
            {
              "id": "7e197620-c1cf-448d-a577-e0f5b354b448",
              "url": "https://jlnjajtcnyqupfaqjerz.supabase.co/storage/v1/object/public/app-images/homepage/79771788-f731-465c-b45b-d85d51d936f8/roomtype_interior/1778033102477-6abvaml4aw.jpg",
              "sortOrder": 7,
              "description": "",
              "isSelected": true,
              "blockId": "298f1b0c-cf66-420c-b465-554e11cbbfb6",
              "category": "roomtype_interior"
            },
            {
              "id": "edc4dda3-fbbd-489e-8369-11a1b7d63a19",
              "url": "https://jlnjajtcnyqupfaqjerz.supabase.co/storage/v1/object/public/app-images/homepage/79771788-f731-465c-b45b-d85d51d936f8/roomtype_interior/1778033102470-m4g3t8pe9l.jpg",
              "sortOrder": 8,
              "description": "",
              "isSelected": true,
              "blockId": "298f1b0c-cf66-420c-b465-554e11cbbfb6",
              "category": "roomtype_interior"
            },
            {
              "id": "fa0a96bd-cea0-46a7-b504-fd8734d10769",
              "url": "https://jlnjajtcnyqupfaqjerz.supabase.co/storage/v1/object/public/app-images/homepage/79771788-f731-465c-b45b-d85d51d936f8/roomtype_exterior/1778033102675-16r3ch18yz.jpg",
              "sortOrder": 0,
              "description": "",
              "isSelected": true,
              "blockId": "298f1b0c-cf66-420c-b465-554e11cbbfb6",
              "category": "roomtype_exterior"
            },
            {
              "id": "42a1d87b-9b76-491e-ab8d-7551f92275d2",
              "url": "https://jlnjajtcnyqupfaqjerz.supabase.co/storage/v1/object/public/app-images/homepage/79771788-f731-465c-b45b-d85d51d936f8/roomtype_exterior/1778033102679-5punzoumjb.jpg",
              "sortOrder": 1,
              "description": "",
              "isSelected": true,
              "blockId": "298f1b0c-cf66-420c-b465-554e11cbbfb6",
              "category": "roomtype_exterior"
            },
            {
              "id": "a13897dd-59cf-4425-894a-8ad5c6900dab",
              "url": "https://jlnjajtcnyqupfaqjerz.supabase.co/storage/v1/object/public/app-images/homepage/79771788-f731-465c-b45b-d85d51d936f8/roomtype_exterior/1778033102777-2p8qsi08n3.jpg",
              "sortOrder": 2,
              "description": "",
              "isSelected": true,
              "blockId": "298f1b0c-cf66-420c-b465-554e11cbbfb6",
              "category": "roomtype_exterior"
            }
          ]
        },
        {
          "id": "b94df7e3-f799-4277-9a04-1aeee3b77d22",
          "images": [
            {
              "id": "e9d1a230-0e11-4434-9460-eacb140ad952",
              "url": "https://jlnjajtcnyqupfaqjerz.supabase.co/storage/v1/object/public/app-images/homepage/79771788-f731-465c-b45b-d85d51d936f8/roomtype_thumbnail/1778033102373-sv042e8x15.jpg",
              "sortOrder": 1,
              "description": "",
              "isSelected": true,
              "blockId": "b94df7e3-f799-4277-9a04-1aeee3b77d22",
              "category": "roomtype_thumbnail"
            },
            {
              "id": "b1252299-cce0-4ed2-9994-9b9739b54b60",
              "url": "https://jlnjajtcnyqupfaqjerz.supabase.co/storage/v1/object/public/app-images/homepage/79771788-f731-465c-b45b-d85d51d936f8/roomtype_interior/1778033102575-sh8i6alah9.jpg",
              "sortOrder": 9,
              "description": "",
              "isSelected": true,
              "blockId": "b94df7e3-f799-4277-9a04-1aeee3b77d22",
              "category": "roomtype_interior"
            },
            {
              "id": "2fa9cd6c-5e19-45f9-9e9d-503ba3fb5e69",
              "url": "https://jlnjajtcnyqupfaqjerz.supabase.co/storage/v1/object/public/app-images/homepage/79771788-f731-465c-b45b-d85d51d936f8/roomtype_interior/1778033102571-zwlte8lvq5.jpg",
              "sortOrder": 10,
              "description": "",
              "isSelected": true,
              "blockId": "b94df7e3-f799-4277-9a04-1aeee3b77d22",
              "category": "roomtype_interior"
            },
            {
              "id": "d0ccfed1-be59-4779-8f6f-898dc746be03",
              "url": "https://jlnjajtcnyqupfaqjerz.supabase.co/storage/v1/object/public/app-images/homepage/79771788-f731-465c-b45b-d85d51d936f8/roomtype_interior/1778033102569-sr9ve9hoa3.jpg",
              "sortOrder": 11,
              "description": "",
              "isSelected": true,
              "blockId": "b94df7e3-f799-4277-9a04-1aeee3b77d22",
              "category": "roomtype_interior"
            },
            {
              "id": "d90af427-d389-4235-be16-1bb461162c07",
              "url": "https://jlnjajtcnyqupfaqjerz.supabase.co/storage/v1/object/public/app-images/homepage/79771788-f731-465c-b45b-d85d51d936f8/roomtype_interior/1778033102524-6pqh8kbu7k.jpg",
              "sortOrder": 12,
              "description": "",
              "isSelected": true,
              "blockId": "b94df7e3-f799-4277-9a04-1aeee3b77d22",
              "category": "roomtype_interior"
            },
            {
              "id": "7281a6b2-b451-4eca-b769-ad81170aa2cc",
              "url": "https://jlnjajtcnyqupfaqjerz.supabase.co/storage/v1/object/public/app-images/homepage/79771788-f731-465c-b45b-d85d51d936f8/roomtype_interior/1778033102573-esjsvn84az.jpg",
              "sortOrder": 13,
              "description": "",
              "isSelected": true,
              "blockId": "b94df7e3-f799-4277-9a04-1aeee3b77d22",
              "category": "roomtype_interior"
            },
            {
              "id": "6df9c17d-38af-41ab-a395-6035d23b441d",
              "url": "https://jlnjajtcnyqupfaqjerz.supabase.co/storage/v1/object/public/app-images/homepage/79771788-f731-465c-b45b-d85d51d936f8/roomtype_interior/1778033102623-ssx4bz6q1u.jpg",
              "sortOrder": 14,
              "description": "",
              "isSelected": true,
              "blockId": "b94df7e3-f799-4277-9a04-1aeee3b77d22",
              "category": "roomtype_interior"
            },
            {
              "id": "7be14b62-886c-4400-a20a-0b72395a9b81",
              "url": "https://jlnjajtcnyqupfaqjerz.supabase.co/storage/v1/object/public/app-images/homepage/79771788-f731-465c-b45b-d85d51d936f8/roomtype_interior/1778033102575-oyz2czeiht.jpg",
              "sortOrder": 15,
              "description": "",
              "isSelected": true,
              "blockId": "b94df7e3-f799-4277-9a04-1aeee3b77d22",
              "category": "roomtype_interior"
            },
            {
              "id": "683205b3-0f87-44dd-888b-b200af7e78b3",
              "url": "https://jlnjajtcnyqupfaqjerz.supabase.co/storage/v1/object/public/app-images/homepage/79771788-f731-465c-b45b-d85d51d936f8/roomtype_interior/1778033102677-rx47p0pxld.jpg",
              "sortOrder": 16,
              "description": "",
              "isSelected": true,
              "blockId": "b94df7e3-f799-4277-9a04-1aeee3b77d22",
              "category": "roomtype_interior"
            },
            {
              "id": "b7bd4107-4831-46a3-b0dc-a1bfa4c02829",
              "url": "https://jlnjajtcnyqupfaqjerz.supabase.co/storage/v1/object/public/app-images/homepage/79771788-f731-465c-b45b-d85d51d936f8/roomtype_interior/1778033102671-1694xsyzam.jpg",
              "sortOrder": 17,
              "description": "",
              "isSelected": true,
              "blockId": "b94df7e3-f799-4277-9a04-1aeee3b77d22",
              "category": "roomtype_interior"
            },
            {
              "id": "cba3f934-5b54-42f0-9302-a5530607bade",
              "url": "https://jlnjajtcnyqupfaqjerz.supabase.co/storage/v1/object/public/app-images/homepage/79771788-f731-465c-b45b-d85d51d936f8/roomtype_exterior/1778033102771-i5prpf1gi6.jpg",
              "sortOrder": 3,
              "description": "",
              "isSelected": true,
              "blockId": "b94df7e3-f799-4277-9a04-1aeee3b77d22",
              "category": "roomtype_exterior"
            },
            {
              "id": "50f8066a-af20-4035-a84c-814e45ca64e9",
              "url": "https://jlnjajtcnyqupfaqjerz.supabase.co/storage/v1/object/public/app-images/homepage/79771788-f731-465c-b45b-d85d51d936f8/roomtype_exterior/1778033102678-9gln7y868r.jpg",
              "sortOrder": 4,
              "description": "",
              "isSelected": true,
              "blockId": "b94df7e3-f799-4277-9a04-1aeee3b77d22",
              "category": "roomtype_exterior"
            },
            {
              "id": "25f1c5f8-3ae3-48f0-82a3-9c2d4e4b504a",
              "url": "https://jlnjajtcnyqupfaqjerz.supabase.co/storage/v1/object/public/app-images/homepage/79771788-f731-465c-b45b-d85d51d936f8/roomtype_exterior/1778033102776-meebrzvn4x.jpg",
              "sortOrder": 5,
              "description": "",
              "isSelected": true,
              "blockId": "b94df7e3-f799-4277-9a04-1aeee3b77d22",
              "category": "roomtype_exterior"
            }
          ]
        },
        {
          "id": "c1207a0e-fb6a-4164-be47-2bb56b97b668",
          "images": [
            {
              "id": "1d6a4bcf-b3ca-4b8b-af33-9247755ddf21",
              "url": "https://jlnjajtcnyqupfaqjerz.supabase.co/storage/v1/object/public/app-images/homepage/79771788-f731-465c-b45b-d85d51d936f8/roomtype_thumbnail/1778033197173-3zugr8ytye.jpg",
              "sortOrder": 2,
              "description": "",
              "isSelected": true,
              "blockId": "c1207a0e-fb6a-4164-be47-2bb56b97b668",
              "category": "roomtype_thumbnail"
            },
            {
              "id": "3b353aef-edc0-4b9e-ae32-34ec5ead698a",
              "url": "https://jlnjajtcnyqupfaqjerz.supabase.co/storage/v1/object/public/app-images/homepage/79771788-f731-465c-b45b-d85d51d936f8/roomtype_interior/1778033197176-m8us0ia9t2.jpg",
              "sortOrder": 18,
              "description": "",
              "isSelected": true,
              "blockId": "c1207a0e-fb6a-4164-be47-2bb56b97b668",
              "category": "roomtype_interior"
            },
            {
              "id": "130395fc-8a0b-40e6-97ed-d27e71788d3f",
              "url": "https://jlnjajtcnyqupfaqjerz.supabase.co/storage/v1/object/public/app-images/homepage/79771788-f731-465c-b45b-d85d51d936f8/roomtype_interior/1778033197170-5af5cd4mjz.jpg",
              "sortOrder": 19,
              "description": "",
              "isSelected": true,
              "blockId": "c1207a0e-fb6a-4164-be47-2bb56b97b668",
              "category": "roomtype_interior"
            },
            {
              "id": "034797e2-ee8e-40b9-bde0-5d7f748048e7",
              "url": "https://jlnjajtcnyqupfaqjerz.supabase.co/storage/v1/object/public/app-images/homepage/79771788-f731-465c-b45b-d85d51d936f8/roomtype_interior/1778033197170-5uvi840ni4.jpg",
              "sortOrder": 20,
              "description": "",
              "isSelected": true,
              "blockId": "c1207a0e-fb6a-4164-be47-2bb56b97b668",
              "category": "roomtype_interior"
            },
            {
              "id": "437377ef-6d7d-4c22-9c2e-82d35a79310c",
              "url": "https://jlnjajtcnyqupfaqjerz.supabase.co/storage/v1/object/public/app-images/homepage/79771788-f731-465c-b45b-d85d51d936f8/roomtype_interior/1778033197272-eqx9gy10go.jpg",
              "sortOrder": 21,
              "description": "",
              "isSelected": true,
              "blockId": "c1207a0e-fb6a-4164-be47-2bb56b97b668",
              "category": "roomtype_interior"
            },
            {
              "id": "3f762c58-8860-4236-a74d-c0d72d1c6ded",
              "url": "https://jlnjajtcnyqupfaqjerz.supabase.co/storage/v1/object/public/app-images/homepage/79771788-f731-465c-b45b-d85d51d936f8/roomtype_interior/1778033197268-979r0b6dzu.jpg",
              "sortOrder": 22,
              "description": "",
              "isSelected": true,
              "blockId": "c1207a0e-fb6a-4164-be47-2bb56b97b668",
              "category": "roomtype_interior"
            },
            {
              "id": "e4932db6-0f19-467d-b9da-d68dddfe6ccd",
              "url": "https://jlnjajtcnyqupfaqjerz.supabase.co/storage/v1/object/public/app-images/homepage/79771788-f731-465c-b45b-d85d51d936f8/roomtype_interior/1778033197175-ie7moyndag.jpg",
              "sortOrder": 23,
              "description": "",
              "isSelected": true,
              "blockId": "c1207a0e-fb6a-4164-be47-2bb56b97b668",
              "category": "roomtype_interior"
            },
            {
              "id": "a9f4d479-eb88-48aa-ad24-c5457e7cc837",
              "url": "https://jlnjajtcnyqupfaqjerz.supabase.co/storage/v1/object/public/app-images/homepage/79771788-f731-465c-b45b-d85d51d936f8/roomtype_interior/1778033197272-3j0xfszykl.jpg",
              "sortOrder": 24,
              "description": "",
              "isSelected": true,
              "blockId": "c1207a0e-fb6a-4164-be47-2bb56b97b668",
              "category": "roomtype_interior"
            },
            {
              "id": "d6342929-b067-4979-8670-a01d7849ca4a",
              "url": "https://jlnjajtcnyqupfaqjerz.supabase.co/storage/v1/object/public/app-images/homepage/79771788-f731-465c-b45b-d85d51d936f8/roomtype_interior/1778033197270-w3k7v61faj.jpg",
              "sortOrder": 25,
              "description": "",
              "isSelected": true,
              "blockId": "c1207a0e-fb6a-4164-be47-2bb56b97b668",
              "category": "roomtype_interior"
            },
            {
              "id": "835ad4be-e210-4883-9cc3-616e92f4a806",
              "url": "https://jlnjajtcnyqupfaqjerz.supabase.co/storage/v1/object/public/app-images/homepage/79771788-f731-465c-b45b-d85d51d936f8/roomtype_exterior/1778033197475-w3mgpfgolp.jpg",
              "sortOrder": 6,
              "description": "",
              "isSelected": true,
              "blockId": "c1207a0e-fb6a-4164-be47-2bb56b97b668",
              "category": "roomtype_exterior"
            },
            {
              "id": "7edcea24-ac9e-4452-854a-81bd67bb381c",
              "url": "https://jlnjajtcnyqupfaqjerz.supabase.co/storage/v1/object/public/app-images/homepage/79771788-f731-465c-b45b-d85d51d936f8/roomtype_exterior/1778033197481-xk6sqq5547.jpg",
              "sortOrder": 7,
              "description": "",
              "isSelected": true,
              "blockId": "c1207a0e-fb6a-4164-be47-2bb56b97b668",
              "category": "roomtype_exterior"
            },
            {
              "id": "d02aa5de-d4e9-4a10-add7-e49f93a85d94",
              "url": "https://jlnjajtcnyqupfaqjerz.supabase.co/storage/v1/object/public/app-images/homepage/79771788-f731-465c-b45b-d85d51d936f8/roomtype_exterior/1778033197475-ggasmvkdn3.jpg",
              "sortOrder": 8,
              "description": "",
              "isSelected": true,
              "blockId": "c1207a0e-fb6a-4164-be47-2bb56b97b668",
              "category": "roomtype_exterior"
            }
          ]
        },
        {
          "id": "8094c6be-3741-4a69-be5d-b35f2f1622a9",
          "images": [
            {
              "id": "c4614dd1-74a2-4dda-93d7-cdd2eba8078c",
              "url": "https://jlnjajtcnyqupfaqjerz.supabase.co/storage/v1/object/public/app-images/homepage/79771788-f731-465c-b45b-d85d51d936f8/roomtype_thumbnail/1778033197168-n7byei7jpr.jpg",
              "sortOrder": 3,
              "description": "",
              "isSelected": true,
              "blockId": "8094c6be-3741-4a69-be5d-b35f2f1622a9",
              "category": "roomtype_thumbnail"
            },
            {
              "id": "fd4fd10c-b7fd-4996-ba4e-eb2214572a45",
              "url": "https://jlnjajtcnyqupfaqjerz.supabase.co/storage/v1/object/public/app-images/homepage/79771788-f731-465c-b45b-d85d51d936f8/roomtype_interior/1778033197276-q8amiev0h1.jpg",
              "sortOrder": 26,
              "description": "",
              "isSelected": true,
              "blockId": "8094c6be-3741-4a69-be5d-b35f2f1622a9",
              "category": "roomtype_interior"
            },
            {
              "id": "5a2ea81c-9608-4597-85e3-207288c51d3a",
              "url": "https://jlnjajtcnyqupfaqjerz.supabase.co/storage/v1/object/public/app-images/homepage/79771788-f731-465c-b45b-d85d51d936f8/roomtype_interior/1778033197275-u30rhmbj5a.jpg",
              "sortOrder": 27,
              "description": "",
              "isSelected": true,
              "blockId": "8094c6be-3741-4a69-be5d-b35f2f1622a9",
              "category": "roomtype_interior"
            },
            {
              "id": "ffb3eb49-6c34-45f8-bc13-e16c3583e7fa",
              "url": "https://jlnjajtcnyqupfaqjerz.supabase.co/storage/v1/object/public/app-images/homepage/79771788-f731-465c-b45b-d85d51d936f8/roomtype_interior/1778033197375-fu32r3rwfm.jpg",
              "sortOrder": 28,
              "description": "",
              "isSelected": true,
              "blockId": "8094c6be-3741-4a69-be5d-b35f2f1622a9",
              "category": "roomtype_interior"
            },
            {
              "id": "5385b29b-bedd-4302-ab85-53439e007e02",
              "url": "https://jlnjajtcnyqupfaqjerz.supabase.co/storage/v1/object/public/app-images/homepage/79771788-f731-465c-b45b-d85d51d936f8/roomtype_interior/1778033197375-70md0gl8u8.jpg",
              "sortOrder": 29,
              "description": "",
              "isSelected": true,
              "blockId": "8094c6be-3741-4a69-be5d-b35f2f1622a9",
              "category": "roomtype_interior"
            },
            {
              "id": "81cbe02b-ecda-4557-814c-933d4e6637f9",
              "url": "https://jlnjajtcnyqupfaqjerz.supabase.co/storage/v1/object/public/app-images/homepage/79771788-f731-465c-b45b-d85d51d936f8/roomtype_interior/1778033197377-vxo3dxga7m.jpg",
              "sortOrder": 30,
              "description": "",
              "isSelected": true,
              "blockId": "8094c6be-3741-4a69-be5d-b35f2f1622a9",
              "category": "roomtype_interior"
            },
            {
              "id": "6172e73c-5dd9-426d-a28c-209c803a3f65",
              "url": "https://jlnjajtcnyqupfaqjerz.supabase.co/storage/v1/object/public/app-images/homepage/79771788-f731-465c-b45b-d85d51d936f8/roomtype_interior/1778033197372-4bzixczg76.jpg",
              "sortOrder": 31,
              "description": "",
              "isSelected": true,
              "blockId": "8094c6be-3741-4a69-be5d-b35f2f1622a9",
              "category": "roomtype_interior"
            },
            {
              "id": "f26a48d3-fb3b-4b01-bd0f-5b5de4d5f047",
              "url": "https://jlnjajtcnyqupfaqjerz.supabase.co/storage/v1/object/public/app-images/homepage/79771788-f731-465c-b45b-d85d51d936f8/roomtype_interior/1778033197373-q381a2el9w.jpg",
              "sortOrder": 32,
              "description": "",
              "isSelected": true,
              "blockId": "8094c6be-3741-4a69-be5d-b35f2f1622a9",
              "category": "roomtype_interior"
            },
            {
              "id": "d2ce24a7-611a-451b-992d-b0a82c024925",
              "url": "https://jlnjajtcnyqupfaqjerz.supabase.co/storage/v1/object/public/app-images/homepage/79771788-f731-465c-b45b-d85d51d936f8/roomtype_interior/1778033197467-kfk9bawpw4.jpg",
              "sortOrder": 33,
              "description": "",
              "isSelected": true,
              "blockId": "8094c6be-3741-4a69-be5d-b35f2f1622a9",
              "category": "roomtype_interior"
            },
            {
              "id": "acea2178-7d94-4bed-9272-9f47b6e6268a",
              "url": "https://jlnjajtcnyqupfaqjerz.supabase.co/storage/v1/object/public/app-images/homepage/79771788-f731-465c-b45b-d85d51d936f8/roomtype_interior/1778033197478-9ak9urex08.jpg",
              "sortOrder": 34,
              "description": "",
              "isSelected": true,
              "blockId": "8094c6be-3741-4a69-be5d-b35f2f1622a9",
              "category": "roomtype_interior"
            },
            {
              "id": "e0f5d2d3-1971-46fe-b1a5-4a27f29e58ae",
              "url": "https://jlnjajtcnyqupfaqjerz.supabase.co/storage/v1/object/public/app-images/homepage/79771788-f731-465c-b45b-d85d51d936f8/roomtype_interior/1778033197480-x0yebgdd8b.jpg",
              "sortOrder": 35,
              "description": "",
              "isSelected": true,
              "blockId": "8094c6be-3741-4a69-be5d-b35f2f1622a9",
              "category": "roomtype_interior"
            },
            {
              "id": "fde7ba03-57d2-4c01-bb09-fc01460e012f",
              "url": "https://jlnjajtcnyqupfaqjerz.supabase.co/storage/v1/object/public/app-images/homepage/79771788-f731-465c-b45b-d85d51d936f8/roomtype_interior/1778033197667-sbk38hgedm.jpg",
              "sortOrder": 36,
              "description": "",
              "isSelected": true,
              "blockId": "8094c6be-3741-4a69-be5d-b35f2f1622a9",
              "category": "roomtype_interior"
            },
            {
              "id": "d6216cc9-c9f4-4020-9165-8ebed1d2d27e",
              "url": "https://jlnjajtcnyqupfaqjerz.supabase.co/storage/v1/object/public/app-images/homepage/79771788-f731-465c-b45b-d85d51d936f8/roomtype_interior/1778033197477-90m1d21zky.jpg",
              "sortOrder": 37,
              "description": "",
              "isSelected": true,
              "blockId": "8094c6be-3741-4a69-be5d-b35f2f1622a9",
              "category": "roomtype_interior"
            },
            {
              "id": "55aa96e7-fb2e-4d90-9d3a-83cbbc59a01b",
              "url": "https://jlnjajtcnyqupfaqjerz.supabase.co/storage/v1/object/public/app-images/homepage/79771788-f731-465c-b45b-d85d51d936f8/roomtype_exterior/1778033197575-8xfgtn09fo.jpg",
              "sortOrder": 9,
              "description": "",
              "isSelected": true,
              "blockId": "8094c6be-3741-4a69-be5d-b35f2f1622a9",
              "category": "roomtype_exterior"
            },
            {
              "id": "85b66f24-dc5a-40ee-a6f5-742844c54cd3",
              "url": "https://jlnjajtcnyqupfaqjerz.supabase.co/storage/v1/object/public/app-images/homepage/79771788-f731-465c-b45b-d85d51d936f8/roomtype_exterior/1778033197570-waswpac27h.jpg",
              "sortOrder": 10,
              "description": "",
              "isSelected": true,
              "blockId": "8094c6be-3741-4a69-be5d-b35f2f1622a9",
              "category": "roomtype_exterior"
            },
            {
              "id": "417cd9bc-d8cf-418f-9235-6bbbc1884d71",
              "url": "https://jlnjajtcnyqupfaqjerz.supabase.co/storage/v1/object/public/app-images/homepage/79771788-f731-465c-b45b-d85d51d936f8/roomtype_exterior/1778033197667-ocnqx1mdnd.jpg",
              "sortOrder": 11,
              "description": "",
              "isSelected": true,
              "blockId": "8094c6be-3741-4a69-be5d-b35f2f1622a9",
              "category": "roomtype_exterior"
            }
          ]
        },
        {
          "id": "9e50933d-e92c-40d1-b5a9-17df7ab199b1",
          "images": [
            {
              "id": "c8f1516d-b15c-44b7-be01-521041bb62cc",
              "url": "https://jlnjajtcnyqupfaqjerz.supabase.co/storage/v1/object/public/app-images/homepage/79771788-f731-465c-b45b-d85d51d936f8/roomtype_thumbnail/1778033508028-nx7dfcyvad.jpg",
              "sortOrder": 4,
              "description": "",
              "isSelected": true,
              "blockId": "9e50933d-e92c-40d1-b5a9-17df7ab199b1",
              "category": "roomtype_thumbnail"
            },
            {
              "id": "d24a1e65-3fe8-49fc-a2c4-3a1baf2e9040",
              "url": "https://jlnjajtcnyqupfaqjerz.supabase.co/storage/v1/object/public/app-images/homepage/79771788-f731-465c-b45b-d85d51d936f8/roomtype_interior/1778033507952-0kjkw8h621.jpg",
              "sortOrder": 38,
              "description": "",
              "isSelected": true,
              "blockId": "9e50933d-e92c-40d1-b5a9-17df7ab199b1",
              "category": "roomtype_interior"
            },
            {
              "id": "3b17c85c-8b82-4191-b849-830ff41a34ca",
              "url": "https://jlnjajtcnyqupfaqjerz.supabase.co/storage/v1/object/public/app-images/homepage/79771788-f731-465c-b45b-d85d51d936f8/roomtype_interior/1778033508031-0dhnmstnta.jpg",
              "sortOrder": 39,
              "description": "",
              "isSelected": true,
              "blockId": "9e50933d-e92c-40d1-b5a9-17df7ab199b1",
              "category": "roomtype_interior"
            },
            {
              "id": "4065a819-ed36-40ef-8c94-5198e0b47565",
              "url": "https://jlnjajtcnyqupfaqjerz.supabase.co/storage/v1/object/public/app-images/homepage/79771788-f731-465c-b45b-d85d51d936f8/roomtype_interior/1778033508030-27winjphev.jpg",
              "sortOrder": 40,
              "description": "",
              "isSelected": true,
              "blockId": "9e50933d-e92c-40d1-b5a9-17df7ab199b1",
              "category": "roomtype_interior"
            },
            {
              "id": "17fc1857-c5e2-4fa1-8915-17a07d5b8235",
              "url": "https://jlnjajtcnyqupfaqjerz.supabase.co/storage/v1/object/public/app-images/homepage/79771788-f731-465c-b45b-d85d51d936f8/roomtype_interior/1778033508025-tpehyatzps.jpg",
              "sortOrder": 41,
              "description": "",
              "isSelected": true,
              "blockId": "9e50933d-e92c-40d1-b5a9-17df7ab199b1",
              "category": "roomtype_interior"
            },
            {
              "id": "0d9b8fbf-55f6-42ce-9cc1-2128fdf9d22e",
              "url": "https://jlnjajtcnyqupfaqjerz.supabase.co/storage/v1/object/public/app-images/homepage/79771788-f731-465c-b45b-d85d51d936f8/roomtype_interior/1778033508027-cht65qn6y2.jpg",
              "sortOrder": 42,
              "description": "",
              "isSelected": true,
              "blockId": "9e50933d-e92c-40d1-b5a9-17df7ab199b1",
              "category": "roomtype_interior"
            },
            {
              "id": "568fe1e8-aab6-4e96-b646-34ecac459507",
              "url": "https://jlnjajtcnyqupfaqjerz.supabase.co/storage/v1/object/public/app-images/homepage/79771788-f731-465c-b45b-d85d51d936f8/roomtype_interior/1778033508125-hsze23lun2.jpg",
              "sortOrder": 43,
              "description": "",
              "isSelected": true,
              "blockId": "9e50933d-e92c-40d1-b5a9-17df7ab199b1",
              "category": "roomtype_interior"
            },
            {
              "id": "14be5414-893f-4ed9-8b3d-010f9b78728f",
              "url": "https://jlnjajtcnyqupfaqjerz.supabase.co/storage/v1/object/public/app-images/homepage/79771788-f731-465c-b45b-d85d51d936f8/roomtype_interior/1778033508067-b6dci60aju.jpg",
              "sortOrder": 44,
              "description": "",
              "isSelected": true,
              "blockId": "9e50933d-e92c-40d1-b5a9-17df7ab199b1",
              "category": "roomtype_interior"
            },
            {
              "id": "cccc94a1-513b-4ab7-9467-ee72f412ab78",
              "url": "https://jlnjajtcnyqupfaqjerz.supabase.co/storage/v1/object/public/app-images/homepage/79771788-f731-465c-b45b-d85d51d936f8/roomtype_interior/1778033508128-mlebjnlzi2.jpg",
              "sortOrder": 45,
              "description": "",
              "isSelected": true,
              "blockId": "9e50933d-e92c-40d1-b5a9-17df7ab199b1",
              "category": "roomtype_interior"
            },
            {
              "id": "f63bf1b9-747d-451b-a09a-612a13ecb160",
              "url": "https://jlnjajtcnyqupfaqjerz.supabase.co/storage/v1/object/public/app-images/homepage/79771788-f731-465c-b45b-d85d51d936f8/roomtype_interior/1778033508131-l2bv08g6o1.jpg",
              "sortOrder": 46,
              "description": "",
              "isSelected": true,
              "blockId": "9e50933d-e92c-40d1-b5a9-17df7ab199b1",
              "category": "roomtype_interior"
            },
            {
              "id": "e191c617-5624-483b-894c-543a0db3a86a",
              "url": "https://jlnjajtcnyqupfaqjerz.supabase.co/storage/v1/object/public/app-images/homepage/79771788-f731-465c-b45b-d85d51d936f8/roomtype_interior/1778033508130-j85gyh9pox.jpg",
              "sortOrder": 47,
              "description": "",
              "isSelected": true,
              "blockId": "9e50933d-e92c-40d1-b5a9-17df7ab199b1",
              "category": "roomtype_interior"
            },
            {
              "id": "360a6f63-620c-4ea0-a228-85315ad5dad2",
              "url": "https://jlnjajtcnyqupfaqjerz.supabase.co/storage/v1/object/public/app-images/homepage/79771788-f731-465c-b45b-d85d51d936f8/roomtype_interior/1778033508127-bhigrs5tw6.jpg",
              "sortOrder": 48,
              "description": "",
              "isSelected": true,
              "blockId": "9e50933d-e92c-40d1-b5a9-17df7ab199b1",
              "category": "roomtype_interior"
            },
            {
              "id": "2b49f8a4-96d9-46be-8bc8-5e6480137a68",
              "url": "https://jlnjajtcnyqupfaqjerz.supabase.co/storage/v1/object/public/app-images/homepage/79771788-f731-465c-b45b-d85d51d936f8/roomtype_exterior/1778033508233-grscto3k65.jpg",
              "sortOrder": 12,
              "description": "",
              "isSelected": true,
              "blockId": "9e50933d-e92c-40d1-b5a9-17df7ab199b1",
              "category": "roomtype_exterior"
            },
            {
              "id": "1d654dba-20ae-4e11-95ad-3d50f07d6244",
              "url": "https://jlnjajtcnyqupfaqjerz.supabase.co/storage/v1/object/public/app-images/homepage/79771788-f731-465c-b45b-d85d51d936f8/roomtype_exterior/1778033508226-9r08y3udsg.jpg",
              "sortOrder": 13,
              "description": "",
              "isSelected": true,
              "blockId": "9e50933d-e92c-40d1-b5a9-17df7ab199b1",
              "category": "roomtype_exterior"
            },
            {
              "id": "604f3cdc-1611-4331-a449-4b897f7c78a7",
              "url": "https://jlnjajtcnyqupfaqjerz.supabase.co/storage/v1/object/public/app-images/homepage/79771788-f731-465c-b45b-d85d51d936f8/roomtype_exterior/1778033508235-an8pldwmfp.jpg",
              "sortOrder": 14,
              "description": "",
              "isSelected": true,
              "blockId": "9e50933d-e92c-40d1-b5a9-17df7ab199b1",
              "category": "roomtype_exterior"
            }
          ]
        },
        {
          "id": "48fea512-d747-4ff0-94ea-7d3d2b379f58",
          "images": [
            {
              "id": "5cbb15d9-dd92-4e36-b817-a43d9ab0128a",
              "url": "https://jlnjajtcnyqupfaqjerz.supabase.co/storage/v1/object/public/app-images/homepage/79771788-f731-465c-b45b-d85d51d936f8/roomtype_thumbnail/1778033659587-bkih8mi53v.jpg",
              "sortOrder": 5,
              "description": "",
              "isSelected": true,
              "blockId": "48fea512-d747-4ff0-94ea-7d3d2b379f58",
              "category": "roomtype_thumbnail"
            },
            {
              "id": "4ba8070f-84e8-40ba-9c11-03eb7b5913c1",
              "url": "https://jlnjajtcnyqupfaqjerz.supabase.co/storage/v1/object/public/app-images/homepage/79771788-f731-465c-b45b-d85d51d936f8/roomtype_interior/1778033659611-facwsc6oyr.jpg",
              "sortOrder": 49,
              "description": "",
              "isSelected": true,
              "blockId": "48fea512-d747-4ff0-94ea-7d3d2b379f58",
              "category": "roomtype_interior"
            },
            {
              "id": "2b7a236e-faca-49f6-b659-cf1735d8e374",
              "url": "https://jlnjajtcnyqupfaqjerz.supabase.co/storage/v1/object/public/app-images/homepage/79771788-f731-465c-b45b-d85d51d936f8/roomtype_interior/1778033659628-fst3ajcq25.jpg",
              "sortOrder": 50,
              "description": "",
              "isSelected": true,
              "blockId": "48fea512-d747-4ff0-94ea-7d3d2b379f58",
              "category": "roomtype_interior"
            },
            {
              "id": "91fcb6e7-d79a-4585-b785-2de1fe927ab4",
              "url": "https://jlnjajtcnyqupfaqjerz.supabase.co/storage/v1/object/public/app-images/homepage/79771788-f731-465c-b45b-d85d51d936f8/roomtype_interior/1778033659627-1stu6clni5.jpg",
              "sortOrder": 51,
              "description": "",
              "isSelected": true,
              "blockId": "48fea512-d747-4ff0-94ea-7d3d2b379f58",
              "category": "roomtype_interior"
            },
            {
              "id": "dc1e7009-4018-4c0a-ad43-ea98231e0597",
              "url": "https://jlnjajtcnyqupfaqjerz.supabase.co/storage/v1/object/public/app-images/homepage/79771788-f731-465c-b45b-d85d51d936f8/roomtype_interior/1778033659626-tikcu4439c.jpg",
              "sortOrder": 52,
              "description": "",
              "isSelected": true,
              "blockId": "48fea512-d747-4ff0-94ea-7d3d2b379f58",
              "category": "roomtype_interior"
            },
            {
              "id": "e8688977-f8f5-4a3c-b89c-e43a16f27e68",
              "url": "https://jlnjajtcnyqupfaqjerz.supabase.co/storage/v1/object/public/app-images/homepage/79771788-f731-465c-b45b-d85d51d936f8/roomtype_interior/1778033659722-32kq3u1izz.jpg",
              "sortOrder": 53,
              "description": "",
              "isSelected": true,
              "blockId": "48fea512-d747-4ff0-94ea-7d3d2b379f58",
              "category": "roomtype_interior"
            },
            {
              "id": "01af2d1f-f9c7-462b-9453-0cf4278e25d5",
              "url": "https://jlnjajtcnyqupfaqjerz.supabase.co/storage/v1/object/public/app-images/homepage/79771788-f731-465c-b45b-d85d51d936f8/roomtype_interior/1778033659635-583wb3o2if.jpg",
              "sortOrder": 54,
              "description": "",
              "isSelected": true,
              "blockId": "48fea512-d747-4ff0-94ea-7d3d2b379f58",
              "category": "roomtype_interior"
            },
            {
              "id": "a173ccd1-739a-4be2-b9d1-8a6402b310af",
              "url": "https://jlnjajtcnyqupfaqjerz.supabase.co/storage/v1/object/public/app-images/homepage/79771788-f731-465c-b45b-d85d51d936f8/roomtype_interior/1778033659670-bjt41ayrc6.jpg",
              "sortOrder": 55,
              "description": "",
              "isSelected": true,
              "blockId": "48fea512-d747-4ff0-94ea-7d3d2b379f58",
              "category": "roomtype_interior"
            },
            {
              "id": "3762abfb-4fb8-4f6f-aaf3-6556533952b9",
              "url": "https://jlnjajtcnyqupfaqjerz.supabase.co/storage/v1/object/public/app-images/homepage/79771788-f731-465c-b45b-d85d51d936f8/roomtype_interior/1778033659672-r0cfd4jko5.jpg",
              "sortOrder": 56,
              "description": "",
              "isSelected": true,
              "blockId": "48fea512-d747-4ff0-94ea-7d3d2b379f58",
              "category": "roomtype_interior"
            },
            {
              "id": "fe6d1273-8c31-4f8b-87f8-99bbce2b1bd1",
              "url": "https://jlnjajtcnyqupfaqjerz.supabase.co/storage/v1/object/public/app-images/homepage/79771788-f731-465c-b45b-d85d51d936f8/roomtype_interior/1778033659669-idusv4sb1x.jpg",
              "sortOrder": 57,
              "description": "",
              "isSelected": true,
              "blockId": "48fea512-d747-4ff0-94ea-7d3d2b379f58",
              "category": "roomtype_interior"
            },
            {
              "id": "73b1f642-458e-430a-b563-f4d2e26114c4",
              "url": "https://jlnjajtcnyqupfaqjerz.supabase.co/storage/v1/object/public/app-images/homepage/79771788-f731-465c-b45b-d85d51d936f8/roomtype_interior/1778033659722-5pdgqotu3f.jpg",
              "sortOrder": 58,
              "description": "",
              "isSelected": true,
              "blockId": "48fea512-d747-4ff0-94ea-7d3d2b379f58",
              "category": "roomtype_interior"
            },
            {
              "id": "6328849b-0778-4b74-8139-b354e7652252",
              "url": "https://jlnjajtcnyqupfaqjerz.supabase.co/storage/v1/object/public/app-images/homepage/79771788-f731-465c-b45b-d85d51d936f8/roomtype_interior/1778033659731-shmwvdg7v6.jpg",
              "sortOrder": 59,
              "description": "",
              "isSelected": true,
              "blockId": "48fea512-d747-4ff0-94ea-7d3d2b379f58",
              "category": "roomtype_interior"
            },
            {
              "id": "071a5b51-aa1e-4a4d-8f8f-ba0adcce3042",
              "url": "https://jlnjajtcnyqupfaqjerz.supabase.co/storage/v1/object/public/app-images/homepage/79771788-f731-465c-b45b-d85d51d936f8/roomtype_interior/1778033659730-0gy4y4w842.jpg",
              "sortOrder": 60,
              "description": "",
              "isSelected": true,
              "blockId": "48fea512-d747-4ff0-94ea-7d3d2b379f58",
              "category": "roomtype_interior"
            },
            {
              "id": "a7c8976f-b7b5-4f57-9035-15ea79c7c96b",
              "url": "https://jlnjajtcnyqupfaqjerz.supabase.co/storage/v1/object/public/app-images/homepage/79771788-f731-465c-b45b-d85d51d936f8/roomtype_exterior/1778033659731-f50g8wirwx.jpg",
              "sortOrder": 15,
              "description": "",
              "isSelected": true,
              "blockId": "48fea512-d747-4ff0-94ea-7d3d2b379f58",
              "category": "roomtype_exterior"
            },
            {
              "id": "1602902d-fbb6-47d5-a683-876819bc4975",
              "url": "https://jlnjajtcnyqupfaqjerz.supabase.co/storage/v1/object/public/app-images/homepage/79771788-f731-465c-b45b-d85d51d936f8/roomtype_exterior/1778033659728-3hoxjzcc6h.jpg",
              "sortOrder": 16,
              "description": "",
              "isSelected": true,
              "blockId": "48fea512-d747-4ff0-94ea-7d3d2b379f58",
              "category": "roomtype_exterior"
            },
            {
              "id": "9cf397cb-77e1-4c88-b042-1aab212661e2",
              "url": "https://jlnjajtcnyqupfaqjerz.supabase.co/storage/v1/object/public/app-images/homepage/79771788-f731-465c-b45b-d85d51d936f8/roomtype_exterior/1778033659768-ef22xxdqao.jpg",
              "sortOrder": 17,
              "description": "",
              "isSelected": true,
              "blockId": "48fea512-d747-4ff0-94ea-7d3d2b379f58",
              "category": "roomtype_exterior"
            }
          ]
        }
      ]
    }
  }
}